{
  "project_info": {
    "project_number": "1085869227798",
    "firebase_url": "https://safety-jacket-71ad8-default-rtdb.asia-southeast1.firebasedatabase.app",
    "project_id": "safety-jacket-71ad8",
    "storage_bucket": "safety-jacket-71ad8.firebasestorage.app"
  },
  "client": [
    {
      "client_info": {
        "mobilesdk_app_id": "1:1085869227798:android:cfbd272975c389a3e31a37",
        "android_client_info": {
          "package_name": "com.example.safetyjacket_app"
        }
      },
      "oauth_client": [],
      "api_key": [
        {
          "current_key": "AIzaSyBhFXk14y2VXlyrmjsXO4TcAbHTVz0kge0"
        }
      ],
      "services": {
        "appinvite_service": {
          "other_platform_oauth_client": []
        }
      }
    }
  ],
  "configuration_version": "1"
}